opentrons_http_api_client-0.2.1.dist-info/licenses/LICENSE
ot_api/__init__.py
ot_api/decorators.py
ot_api/health.py
ot_api/labware.py
ot_api/lh.py
ot_api/modules.py
ot_api/requestor.py
ot_api/runs.py
opentrons_http_api_client-0.2.1.dist-info/METADATA
opentrons_http_api_client-0.2.1.dist-info/WHEEL
opentrons_http_api_client-0.2.1.dist-info/top_level.txt
opentrons_http_api_client-0.2.1.dist-info/RECORD
