Metadata-Version: 2.4
Name: opentrons_http_api_client
Version: 0.2.1
Summary: A Python library for interacting with the Opentrons HTTP API
Home-page: https://github.com/rickwierenga/opentrons-python-api.git
Requires-Python: >=3.7
License-File: LICENSE
Dynamic: description
Dynamic: description-content-type
Dynamic: home-page
Dynamic: license-file
Dynamic: requires-python
Dynamic: summary
